README.md
setup.py
damefaces/__init__.py
damefaces.egg-info/PKG-INFO
damefaces.egg-info/SOURCES.txt
damefaces.egg-info/dependency_links.txt
damefaces.egg-info/not-zip-safe
damefaces.egg-info/requires.txt
damefaces.egg-info/top_level.txt
damefaces/bin/__init__.py
damefaces/bin/age_deploy.prototxt
damefaces/bin/age_net.caffemodel
damefaces/bin/damefaces.py
damefaces/bin/gender_deploy.prototxt
damefaces/bin/gender_net.caffemodel
damefaces/bin/opencv_face_detector.pbtxt
damefaces/bin/opencv_face_detector_uint8.pb
damefaces/files/girl1.jpg
damefaces/files/girl2.jpg
damefaces/files/kid1.jpg
damefaces/files/kid2.jpg
damefaces/files/man1.jpg
damefaces/files/man2.jpg