Metadata-Version: 1.1
Name: damefaces
Version: 0.0.2.post9
Summary: Learning Faces from Tests by David Arroyo Menéndez
Home-page: http://github.com/davidam/damefaces
Author: David Arroyo Menéndez
Author-email: davidam@gmail.com
License: GPLv3
Keywords: faces tests
Platform: UNKNOWN
Classifier: Development Status :: 3 - Alpha
Classifier: License :: OSI Approved :: GNU General Public License v3 (GPLv3)
Classifier: Programming Language :: Python :: 3.6
Classifier: Topic :: Scientific/Engineering
